Metadata-Version: 1.1
Name: tolissoexample
Version: 0.1.3
Summary: A example Python package
Home-page: https://github.com/shuds13/pyexample
Author: Stephen Hudson
Author-email: shudson@anl.gov
License: BSD 2-clause
Platform: UNKNOWN
Classifier: Development Status :: 1 - Planning
Classifier: Intended Audience :: Science/Research
Classifier: License :: OSI Approved :: BSD License
Classifier: Operating System :: POSIX :: Linux
Classifier: Programming Language :: Python :: 3
Classifier: Programming Language :: Python :: 3.4
Classifier: Programming Language :: Python :: 3.5
